ram.v
module ram(
	input [31:0] address,
	input [31:0] data,
	input write,
	input clk,
	output response,
	output [31:0] out
);

parameter size = 4096;
reg [31:0] ram [size - 1:0];

reg [31:0] prev_address;
reg [31:0] prev_data;
reg [31:0] prev_out;
reg prev_write;
reg prev_response;

initial 
begin
	prev_address = address % size;
	prev_data = 0;
	prev_response = 0;
	prev_write = 0;
end

always @(posedge clk)
begin
	if ((prev_address != address % size) || (prev_data != data) || (prev_write != write))
	begin
		prev_address = address % size;
		prev_data = data;
		prev_write = write;
		prev_response = 1;
	end
	else
		if (prev_response) 
		begin
			if (write)
				ram[prev_address] = data;
			else
				prev_out = ram[prev_address];
			prev_response = 0;
		end
end

assign out = prev_out;
assign response = prev_response;

endmodule

ram_testbench.v
module ram_testbench;

reg [0:31] address, data;
reg write, clk;
wire [0:31] out;

ram ram(
	.address(address), 
	.data(data), 
	.write(write), 
	.clk(clk), 
	.out(out)
);

initial
begin
	clk = 1'b0;
	
	address = 32'b00000000000000000000000000000000;			// 0
	data =    32'b00000000000000000011100011000000;			// 14528
	write = 1;
	
	#100
	address = 32'b10100111111001011111101111011100;			// 2816867292 % size = 3036
	data =    32'b00000000000010000000100001010101;			// 526421
	write = 1;
	
	#100
	address = 32'b00000000000000000000000000000000;			// 0
	data =    32'b00000000000000000011100011000000;			// 14528
	write = 0;
	
	#100
	address = 32'b10100111111001011111101111011100;			// 2816867292 % size = 3036
	data =    32'b00000000000010000000100001010101;			// 526421
	write = 0;
	
	#100
	address = 32'b00000000000011110100011111010001;			// 1001425 % size = 2001
	data =    32'b00000001100000110001101100010110;			// 25369366
	write = 1;

	#100
	address = 32'b00000000000011110100011111010001;			// 1001425 % size = 2001
	data =    32'b00000001100000110001101100010110;			// 25369366
	write = 0;

	#100
	address = 32'b10100111111001011111101111011100;			// 2816867292 % size = 3036
	data =    32'b00000000000000000011100011000000;			// 14528
	write = 1;

	#100
	address = 32'b10100111111001011111101111011100;			// 2816867292 % size = 3036
	data =    32'b00000000000000000011100011000000;			// 14528
	write = 0;
end

initial
$monitor("address = %d data = %d write = %d out = %d", address % 4096, data, write, out);

initial
$dumpvars;

always #25 clk = ~clk;
endmodule

dump.vcd
$date
	Sun Oct 21 13:44:14 2018
$end
$version
	ModelSim Version 10.5b
$end
$timescale
	1ps
$end

$scope module ram_testbench $end
$var reg 32 ! address [0:31] $end
$var reg 32 " data [0:31] $end
$var reg 1 # write $end
$var reg 1 $ clk $end
$var wire 1 % out [0] $end
$var wire 1 & out [1] $end
$var wire 1 ' out [2] $end
$var wire 1 ( out [3] $end
$var wire 1 ) out [4] $end
$var wire 1 * out [5] $end
$var wire 1 + out [6] $end
$var wire 1 , out [7] $end
$var wire 1 - out [8] $end
$var wire 1 . out [9] $end
$var wire 1 / out [10] $end
$var wire 1 0 out [11] $end
$var wire 1 1 out [12] $end
$var wire 1 2 out [13] $end
$var wire 1 3 out [14] $end
$var wire 1 4 out [15] $end
$var wire 1 5 out [16] $end
$var wire 1 6 out [17] $end
$var wire 1 7 out [18] $end
$var wire 1 8 out [19] $end
$var wire 1 9 out [20] $end
$var wire 1 : out [21] $end
$var wire 1 ; out [22] $end
$var wire 1 < out [23] $end
$var wire 1 = out [24] $end
$var wire 1 > out [25] $end
$var wire 1 ? out [26] $end
$var wire 1 @ out [27] $end
$var wire 1 A out [28] $end
$var wire 1 B out [29] $end
$var wire 1 C out [30] $end
$var wire 1 D out [31] $end

$scope module ram $end
$var parameter 32 E size $end
$var wire 1 F address [31] $end
$var wire 1 G address [30] $end
$var wire 1 H address [29] $end
$var wire 1 I address [28] $end
$var wire 1 J address [27] $end
$var wire 1 K address [26] $end
$var wire 1 L address [25] $end
$var wire 1 M address [24] $end
$var wire 1 N address [23] $end
$var wire 1 O address [22] $end
$var wire 1 P address [21] $end
$var wire 1 Q address [20] $end
$var wire 1 R address [19] $end
$var wire 1 S address [18] $end
$var wire 1 T address [17] $end
$var wire 1 U address [16] $end
$var wire 1 V address [15] $end
$var wire 1 W address [14] $end
$var wire 1 X address [13] $end
$var wire 1 Y address [12] $end
$var wire 1 Z address [11] $end
$var wire 1 [ address [10] $end
$var wire 1 \ address [9] $end
$var wire 1 ] address [8] $end
$var wire 1 ^ address [7] $end
$var wire 1 _ address [6] $end
$var wire 1 ` address [5] $end
$var wire 1 a address [4] $end
$var wire 1 b address [3] $end
$var wire 1 c address [2] $end
$var wire 1 d address [1] $end
$var wire 1 e address [0] $end
$var wire 1 f data [31] $end
$var wire 1 g data [30] $end
$var wire 1 h data [29] $end
$var wire 1 i data [28] $end
$var wire 1 j data [27] $end
$var wire 1 k data [26] $end
$var wire 1 l data [25] $end
$var wire 1 m data [24] $end
$var wire 1 n data [23] $end
$var wire 1 o data [22] $end
$var wire 1 p data [21] $end
$var wire 1 q data [20] $end
$var wire 1 r data [19] $end
$var wire 1 s data [18] $end
$var wire 1 t data [17] $end
$var wire 1 u data [16] $end
$var wire 1 v data [15] $end
$var wire 1 w data [14] $end
$var wire 1 x data [13] $end
$var wire 1 y data [12] $end
$var wire 1 z data [11] $end
$var wire 1 { data [10] $end
$var wire 1 | data [9] $end
$var wire 1 } data [8] $end
$var wire 1 ~ data [7] $end
$var wire 1 !! data [6] $end
$var wire 1 "! data [5] $end
$var wire 1 #! data [4] $end
$var wire 1 $! data [3] $end
$var wire 1 %! data [2] $end
$var wire 1 &! data [1] $end
$var wire 1 '! data [0] $end
$var wire 1 (! write $end
$var wire 1 )! clk $end
$var wire 1 *! response $end
$var wire 1 % out [31] $end
$var wire 1 & out [30] $end
$var wire 1 ' out [29] $end
$var wire 1 ( out [28] $end
$var wire 1 ) out [27] $end
$var wire 1 * out [26] $end
$var wire 1 + out [25] $end
$var wire 1 , out [24] $end
$var wire 1 - out [23] $end
$var wire 1 . out [22] $end
$var wire 1 / out [21] $end
$var wire 1 0 out [20] $end
$var wire 1 1 out [19] $end
$var wire 1 2 out [18] $end
$var wire 1 3 out [17] $end
$var wire 1 4 out [16] $end
$var wire 1 5 out [15] $end
$var wire 1 6 out [14] $end
$var wire 1 7 out [13] $end
$var wire 1 8 out [12] $end
$var wire 1 9 out [11] $end
$var wire 1 : out [10] $end
$var wire 1 ; out [9] $end
$var wire 1 < out [8] $end
$var wire 1 = out [7] $end
$var wire 1 > out [6] $end
$var wire 1 ? out [5] $end
$var wire 1 @ out [4] $end
$var wire 1 A out [3] $end
$var wire 1 B out [2] $end
$var wire 1 C out [1] $end
$var wire 1 D out [0] $end
$var reg 32 +! prev_address [31:0] $end
$var reg 32 ,! prev_data [31:0] $end
$var reg 32 -! prev_out [31:0] $end
$var reg 1 .! prev_write $end
$var reg 1 /! prev_response $end
$upscope $end
$upscope $end
$enddefinitions $end
#0
$dumpvars
b0 !
b11100011000000 "
1#
0$
bx +!
b0 ,!
bx -!
0.!
0/!
b1000000000000 E
xD
xC
xB
xA
x@
x?
x>
x=
x<
x;
x:
x9
x8
x7
x6
x5
x4
x3
x2
x1
x0
x/
x.
x-
x,
x+
x*
x)
x(
x'
x&
x%
0)!
1(!
0'!
0&!
0%!
0$!
0#!
0"!
1!!
1~
0}
0|
0{
1z
1y
1x
0w
0v
0u
0t
0s
0r
0q
0p
0o
0n
0m
0l
0k
0j
0i
0h
0g
0f
0e
0d
0c
0b
0a
0`
0_
0^
0]
0\
0[
0Z
0Y
0X
0W
0V
0U
0T
0S
0R
0Q
0P
0O
0N
0M
0L
0K
0J
0I
0H
0G
0F
0*!
$end
#25
1$
1)!
b0 +!
b11100011000000 ,!
1.!
1/!
1*!
#50
0$
0)!
#75
1$
1)!
0/!
0*!
#100
b10100111111001011111101111011100 !
b10000000100001010101 "
0$
1'!
1%!
1#!
0~
0y
0x
1r
1c
1b
1a
1_
1^
1]
1\
1Z
1Y
1X
1W
1V
1U
1S
1P
1O
1N
1M
1L
1K
1H
1F
0)!
#125
1$
1)!
b101111011100 +!
b10000000100001010101 ,!
1/!
1*!
#150
0$
0)!
#175
1$
1)!
0/!
0*!
#200
b0 !
b11100011000000 "
0#
0$
0'!
0%!
0#!
1~
1y
1x
0r
0c
0b
0a
0_
0^
0]
0\
0Z
0Y
0X
0W
0V
0U
0S
0P
0O
0N
0M
0L
0K
0H
0F
0(!
0)!
#225
1$
1)!
b0 +!
b11100011000000 ,!
0.!
1/!
1*!
#250
0$
0)!
#275
1$
1)!
b11100011000000 -!
0/!
0D
0C
0B
0A
0@
0?
1>
1=
0<
0;
0:
19
18
17
06
05
04
03
02
01
00
0/
0.
0-
0,
0+
0*
0)
0(
0'
0&
0%
0*!
#300
b10100111111001011111101111011100 !
b10000000100001010101 "
0$
1'!
1%!
1#!
0~
0y
0x
1r
1c
1b
1a
1_
1^
1]
1\
1Z
1Y
1X
1W
1V
1U
1S
1P
1O
1N
1M
1L
1K
1H
1F
0)!
#325
1$
1)!
b101111011100 +!
b10000000100001010101 ,!
1/!
1*!
#350
0$
0)!
#375
1$
1)!
b10000000100001010101 -!
0/!
1D
1B
1@
0=
08
07
11
0*!
#400
b11110100011111010001 !
b1100000110001101100010110 "
1#
0$
0'!
1&!
0!!
1}
1|
1y
1u
1t
0r
1n
1m
1e
0c
0b
1[
0Z
0Y
0X
0V
1T
1R
0P
0O
0N
0M
0L
0K
0H
0F
1(!
0)!
#425
1$
1)!
b11111010001 +!
b1100000110001101100010110 ,!
1.!
1/!
1*!
#450
0$
0)!
#475
1$
1)!
0/!
0*!
#500
0#
0$
0(!
0)!
#525
1$
1)!
0.!
1/!
1*!
#550
0$
0)!
#575
1$
1)!
b1100000110001101100010110 -!
0/!
0D
1C
0>
1<
1;
18
14
13
01
1-
1,
0*!
#600
b10100111111001011111101111011100 !
b11100011000000 "
1#
0$
0&!
0%!
0#!
1!!
1~
0}
0|
1x
0u
0t
0n
0m
0e
1c
1b
0[
1Z
1Y
1X
1V
0T
0R
1P
1O
1N
1M
1L
1K
1H
1F
1(!
0)!
#625
1$
1)!
b101111011100 +!
b11100011000000 ,!
1.!
1/!
1*!
#650
0$
0)!
#675
1$
1)!
0/!
0*!
#700
0#
0$
0(!
0)!
#725
1$
1)!
0.!
1/!
1*!
#750
0$
0)!
#775
1$
1)!
b11100011000000 -!
0/!
0C
0B
0@
1>
1=
0<
0;
17
04
03
0-
0,
0*!
